MANIFEST.in
setup.py
gitignore/Actionscript.gitignore
gitignore/Ada.gitignore
gitignore/Agda.gitignore
gitignore/Android.gitignore
gitignore/AppEngine.gitignore
gitignore/AppceleratorTitanium.gitignore
gitignore/ArchLinuxPackages.gitignore
gitignore/Autotools.gitignore
gitignore/C++.gitignore
gitignore/C.gitignore
gitignore/CFWheels.gitignore
gitignore/CMake.gitignore
gitignore/CONTRIBUTING.md
gitignore/CUDA.gitignore
gitignore/CakePHP.gitignore
gitignore/ChefCookbook.gitignore
gitignore/Clojure.gitignore
gitignore/CodeIgniter.gitignore
gitignore/CommonLisp.gitignore
gitignore/Composer.gitignore
gitignore/Concrete5.gitignore
gitignore/Coq.gitignore
gitignore/CraftCMS.gitignore
gitignore/D.gitignore
gitignore/DM.gitignore
gitignore/Dart.gitignore
gitignore/Delphi.gitignore
gitignore/Drupal.gitignore
gitignore/EPiServer.gitignore
gitignore/Eagle.gitignore
gitignore/Elisp.gitignore
gitignore/Elixir.gitignore
gitignore/Elm.gitignore
gitignore/Erlang.gitignore
gitignore/ExpressionEngine.gitignore
gitignore/ExtJs.gitignore
gitignore/Fancy.gitignore
gitignore/Finale.gitignore
gitignore/ForceDotCom.gitignore
gitignore/Fortran.gitignore
gitignore/FuelPHP.gitignore
gitignore/GWT.gitignore
gitignore/Gcov.gitignore
gitignore/GitBook.gitignore
gitignore/Go.gitignore
gitignore/Godot.gitignore
gitignore/Gradle.gitignore
gitignore/Grails.gitignore
gitignore/Haskell.gitignore
gitignore/IGORPro.gitignore
gitignore/Idris.gitignore
gitignore/Java.gitignore
gitignore/Jboss.gitignore
gitignore/Jekyll.gitignore
gitignore/Joomla.gitignore
gitignore/Julia.gitignore
gitignore/KiCad.gitignore
gitignore/Kohana.gitignore
gitignore/Kotlin.gitignore
gitignore/LICENSE
gitignore/LabVIEW.gitignore
gitignore/Laravel.gitignore
gitignore/Leiningen.gitignore
gitignore/LemonStand.gitignore
gitignore/Lilypond.gitignore
gitignore/Lithium.gitignore
gitignore/Lua.gitignore
gitignore/Magento.gitignore
gitignore/Maven.gitignore
gitignore/Mercury.gitignore
gitignore/MetaProgrammingSystem.gitignore
pygig.egg-info/PKG-INFO
pygig.egg-info/SOURCES.txt
pygig.egg-info/dependency_links.txt
pygig.egg-info/entry_points.txt
pygig.egg-info/requires.txt
pygig.egg-info/top_level.txt