Metadata-Version: 1.0
Name: pygig
Version: 1.0.6
Summary: A command tool to generate .gitignore file.
Home-page: https://github.com/1033020837/GitIgnoreGenerator
Author: lyq
Author-email: 1033020837@qq.com
License: UNKNOWN
Platform: UNKNOWN
